trilearn/__init__.py
trilearn/auxiliary_functions.py
trilearn/graph_predictive.py
trilearn/mh_greenthomas.py
trilearn/mh_nodedriven.py
trilearn/pgibbs.py
trilearn/set_process.py
trilearn/smc.py
trilearn/distributions/__init__.py
trilearn/distributions/dirichlet.py
trilearn/distributions/discrete_dec_log_linear.py
trilearn/distributions/g_intra_class.py
trilearn/distributions/g_inv_wishart.py
trilearn/distributions/gaussian_graphical_model.py
trilearn/distributions/matrix_multivariate_normal.py
trilearn/distributions/multivariate_students_t.py
trilearn/distributions/sequential_junction_tree_distributions.py
trilearn/distributions/wishart.py
trilearn/graph/__init__.py
trilearn/graph/decomposable.py
trilearn/graph/empirical_graph_distribution.py
trilearn/graph/graph.py
trilearn/graph/greenthomas.py
trilearn/graph/junction_tree.py
trilearn/graph/junction_tree_collapser.py
trilearn/graph/junction_tree_expander.py
trilearn/graph/subtree_sampler.py
trilearn/graph/trajectory.py
trilearn-2.0.5.data/scripts/analyze_graph_trajectories
trilearn-2.0.5.data/scripts/count_chordal_graphs
trilearn-2.0.5.data/scripts/gen_g-intraclass_precmat
trilearn-2.0.5.data/scripts/mh_ggm_sample
trilearn-2.0.5.data/scripts/pgibbs_ggm_sample
trilearn-2.0.5.data/scripts/pgibbs_loglinear_sample
trilearn-2.0.5.data/scripts/pgibbs_uniform_jt_sample
trilearn-2.0.5.data/scripts/sample_cta
trilearn-2.0.5.data/scripts/sample_g-inv_wish
trilearn-2.0.5.data/scripts/sample_ggm_AR_data
trilearn-2.0.5.data/scripts/sample_ggm_intraclass_data
trilearn-2.0.5.data/scripts/sample_loglinear_data
trilearn-2.0.5.data/scripts/sample_loglinear_parameters
trilearn-2.0.5.data/scripts/sample_normal_data
trilearn-2.0.5.data/scripts/smc_ggm_analyze
trilearn-2.0.5.data/scripts/smc_ggm_sample
trilearn-2.0.5.dist-info/LICENSE
trilearn-2.0.5.dist-info/METADATA
trilearn-2.0.5.dist-info/WHEEL
trilearn-2.0.5.dist-info/top_level.txt
trilearn-2.0.5.dist-info/RECORD
