Metadata-Version: 2.1
Name: trilearn
Version: 2.0.5
Summary: Bayesian predictive classification and structure learning in decomposable graphical models using particle Gibbs.
Home-page: https://github.com/felixleopoldo/trilearn
Author: Felix Rios
Author-email: felix.leopoldo.rios@gmail.com
License: Apache 2.0
Download-URL: https://github.com/felixleopoldo/trilearn/archive/2.0.5.tar.gz
Platform: UNKNOWN
Classifier: Development Status :: 5 - Production/Stable
Classifier: Intended Audience :: Science/Research
Classifier: Operating System :: OS Independent
Classifier: Programming Language :: Python
Classifier: Programming Language :: Python :: 3.11
Requires-Python: >3.0
Requires-Dist: seaborn (>=0.12.2)
Requires-Dist: pandas (>=2.0.0)
Requires-Dist: numpy (>=1.13.0)
Requires-Dist: matplotlib (>=3.0.0)
Requires-Dist: ipywidgets (>=7.0.0)
Requires-Dist: scipy (>=1.0.0)
Requires-Dist: networkx (>=3.1)
Requires-Dist: scikit-learn (>=0.18.0)
Requires-Dist: tqdm (>=4.18.0)
Requires-Dist: pygraphviz (>=1.2.0)
Requires-Dist: tabulate
Requires-Dist: nose2
Requires-Dist: sphinx-rtd-theme
